{"timesteps_total": 1600, "episodes_total": 132, "approx_exploitability": 0.7661}
{"timesteps_total": 3200000, "episodes_total": 266664, "approx_exploitability": 0.7359}
{"timesteps_total": 6400000, "episodes_total": 533332, "approx_exploitability": 0.7763}
{"timesteps_total": 9600000, "episodes_total": 800000, "approx_exploitability": 0.7294}
{"timesteps_total": 12800000, "episodes_total": 1066664, "approx_exploitability": 0.6403}
{"timesteps_total": 16000000, "episodes_total": 1333332, "approx_exploitability": 0.5364}
{"timesteps_total": 19200000, "episodes_total": 1600000, "approx_exploitability": 0.5924}
{"timesteps_total": 22400000, "episodes_total": 1866664, "approx_exploitability": 0.6093999999999999}
{"timesteps_total": 25600000, "episodes_total": 2133332, "approx_exploitability": 0.6181}
{"timesteps_total": 28800000, "episodes_total": 2400000, "approx_exploitability": 0.4901}
{"timesteps_total": 32000000, "episodes_total": 2666664, "approx_exploitability": 0.6132}
{"timesteps_total": 35200000, "episodes_total": 2933332, "approx_exploitability": 0.4907}
{"timesteps_total": 38400000, "episodes_total": 3200000, "approx_exploitability": 0.63}
{"timesteps_total": 41600000, "episodes_total": 3466664, "approx_exploitability": 0.4554}
{"timesteps_total": 44800000, "episodes_total": 3733332, "approx_exploitability": 0.6}
{"timesteps_total": 48000000, "episodes_total": 4000000, "approx_exploitability": 0.4777}
{"timesteps_total": 51200000, "episodes_total": 4266664, "approx_exploitability": 0.5509}
{"timesteps_total": 54400000, "episodes_total": 4533332, "approx_exploitability": 0.5354}
{"timesteps_total": 57600000, "episodes_total": 4800000, "approx_exploitability": 0.5622}
{"timesteps_total": 60800000, "episodes_total": 5066664, "approx_exploitability": 0.7053}
{"timesteps_total": 64000000, "episodes_total": 5333332, "approx_exploitability": 0.5064}
{"timesteps_total": 67200000, "episodes_total": 5600000, "approx_exploitability": 0.5637}
{"timesteps_total": 70400000, "episodes_total": 5866664, "approx_exploitability": 0.5408999999999999}
{"timesteps_total": 73600000, "episodes_total": 6133332, "approx_exploitability": 0.4919}
{"timesteps_total": 76800000, "episodes_total": 6400000, "approx_exploitability": 0.5454}
{"timesteps_total": 80000000, "episodes_total": 6666664, "approx_exploitability": 0.5059}
{"timesteps_total": 83200000, "episodes_total": 6933332, "approx_exploitability": 0.4521}
{"timesteps_total": 86400000, "episodes_total": 7200000, "approx_exploitability": 0.4203}
{"timesteps_total": 89600000, "episodes_total": 7466664, "approx_exploitability": 0.5679000000000001}
{"timesteps_total": 92800000, "episodes_total": 7733332, "approx_exploitability": 0.6035999999999999}
{"timesteps_total": 96000000, "episodes_total": 8000000, "approx_exploitability": 0.37960000000000005}
{"timesteps_total": 99200000, "episodes_total": 8266664, "approx_exploitability": 0.5124}
{"timesteps_total": 102400000, "episodes_total": 8533332, "approx_exploitability": 0.5114000000000001}
{"timesteps_total": 105600000, "episodes_total": 8800000, "approx_exploitability": 0.4941}
{"timesteps_total": 108800000, "episodes_total": 9066664, "approx_exploitability": 0.5801999999999999}
{"timesteps_total": 112000000, "episodes_total": 9333332, "approx_exploitability": 0.5697}
{"timesteps_total": 115200000, "episodes_total": 9600000, "approx_exploitability": 0.5476000000000001}
{"timesteps_total": 118400000, "episodes_total": 9866664, "approx_exploitability": 0.5053}
{"timesteps_total": 121600000, "episodes_total": 10133332, "approx_exploitability": 0.5912999999999999}
{"timesteps_total": 124000000, "episodes_total": 10333328, "approx_exploitability": 0.4282}
{"timesteps_total": 127200000, "episodes_total": 10599996, "approx_exploitability": 0.5458000000000001}
{"timesteps_total": 130400000, "episodes_total": 10866664, "approx_exploitability": 0.5897}
{"timesteps_total": 133600000, "episodes_total": 11133328, "approx_exploitability": 0.5585}
{"timesteps_total": 136800000, "episodes_total": 11399996, "approx_exploitability": 0.5179}
{"timesteps_total": 140000000, "episodes_total": 11666664, "approx_exploitability": 0.5468}
{"timesteps_total": 143200000, "episodes_total": 11933328, "approx_exploitability": 0.5593}
{"timesteps_total": 146400000, "episodes_total": 12199996, "approx_exploitability": 0.6324000000000001}
{"timesteps_total": 149600000, "episodes_total": 12466664, "approx_exploitability": 0.5349999999999999}
{"timesteps_total": 152800000, "episodes_total": 12733328, "approx_exploitability": 0.4467}
{"timesteps_total": 156000000, "episodes_total": 12999996, "approx_exploitability": 0.5558000000000001}
{"timesteps_total": 159200000, "episodes_total": 13266664, "approx_exploitability": 0.6040000000000001}
{"timesteps_total": 162400000, "episodes_total": 13533328, "approx_exploitability": 0.4749}
{"timesteps_total": 165600000, "episodes_total": 13799996, "approx_exploitability": 0.5047}
{"timesteps_total": 168800000, "episodes_total": 14066664, "approx_exploitability": 0.5135}
{"timesteps_total": 172000000, "episodes_total": 14333328, "approx_exploitability": 0.6164000000000001}
